Workbook

Sheet README
A1: Inventory Optimization & Demand Analysis
A2: Excel reporting layer | Source: retail_store_inventory.csv | 73,100 rows | 2022-01-01 to 2024-01-01
A5: SHEETS
A6: Parameters | B6: The only sheet you edit. Yellow cells with blue text are inputs. Changing a cover threshold re-classifies the Action Register and the scorecard flags.
A7: Action_Register | B7: The decision list: all 100 stock positions as at 2024-01-01, each with a live status and recommended action. This is the sheet a manager uses.
A8: SKU_Scorecard | B8: One row per store-product. Reports how OFTEN each position falls critical or excess across 731 days, with a noise-band test on whether the gap is real.
A9: Monthly_Summary | B9: 25 monthly periods. Complete Month = 0 marks a partial period.
A10: Store_Summary | B10: Store roll-up via SUMIF / AVERAGEIF / COUNTIFS over the scorecard.
A11: KPI_Dashboard | B11: Headline KPIs, all formula-driven.
A12: Data_Dictionary | B12: Every source and derived field with its definition.
A13: Raw_Sample | B13: First 500 source rows. Full file at data/raw/.
A15: COLOUR LEGEND
A16: Blue text on yellow fill | B16: Input cell - safe to edit
A17: Black text | B17: Formula - do not overwrite
A18: Grey fill | B18: Aggregated fact imported from the Python build step
A20: WHY CLASSIFICATION IS PER DAY, NOT PER PRODUCT
A21: The exposure is episodic | B21: Averaged over 731 days every store-SKU sits near 2.0 days of cover and looks healthy. The risk appears on individual days, so the unit of decision is the position-day, not the product.
A22: Noise band | B22: Each position has 731 daily observations, giving a binomial standard error of about 1.45pp on an exception rate. Gaps under roughly 4pp between positions are sampling noise, and the scorecard says so rather than ranking them anyway.
A24: KEY ASSUMPTIONS
A25: No cost column exists | B25: Inventory is valued at RETAIL price. Margin and cost-based turnover cannot be computed from this dataset.
A26: No reorder level column | B26: The reorder point is derived as Average Daily Demand x the Reorder Cover parameter. It is a stated policy, not a source field.
A27: No lead time or supplier | B27: Those KPIs are excluded rather than invented.
A28: Category and Region | B28: Vary row-to-row within the same store-product, so they are transaction labels, not product or store attributes. No decision rests on them.

Sheet Parameters
A1: Policy Parameters
A2: Edit the yellow cells. Every classification in this workbook reads from here.
A4: Parameter | B4: Value | C4: Basis
A5: Critical cover threshold (days) | B5: 1 | C5: Below this, stock covers under one day of demand. Action = REPLENISH NOW.
A6: Reorder cover threshold (days) | B6: 1.5 | C6: Reorder point in days of demand. Set near the 25th percentile of observed cover (1.19 days).
A7: Target cover (days) | B7: 3 | C7: Stock above this is excess. Set near the 75th percentile of observed cover (2.84 days).
A8: Analysis period (days) | B8: 731 | C8: Days in the source panel: 2022-01-01 to 2024-01-01 inclusive.
A9: Days per year | B9: 365.25 | C9: Used to annualise inventory turnover.
A10: System critical rate (%) | B10: 18.68 | C10: Share of all 73,100 position-days classified Critical. Centre of the noise band.
A11: System excess rate (%) | B11: 19.11 | C11: Share of all 73,100 position-days classified Excess. Centre of the noise band.
A12: Noise band width (std errors) | B12: 2.8 | C12: Largest deviation expected from chance across 100 positions. Beyond this, a gap is real.
A14: Derived noise band (calculated)
A15: Critical std error per position (pp) | B15: =SQRT(($B$10/100)*(1-$B$10/100)/$B$8)*100 -> 1.4415458
A16: Critical rate lower bound (%) | B16: =$B$10-$B$12*$B$15 -> 14.643672
A17: Critical rate upper bound (%) | B17: =$B$10+$B$12*$B$15 -> 22.716328
A18: Excess std error per position (pp) | B18: =SQRT(($B$11/100)*(1-$B$11/100)/$B$8)*100 -> 1.454183
A19: Excess rate lower bound (%) | B19: =$B$11-$B$12*$B$18 -> 15.038288
A20: Excess rate upper bound (%) | B20: =$B$11+$B$12*$B$18 -> 23.181712

Sheet Action_Register
A1: Action Register - Stock Position as at 2024-01-01
A2: All 100 store-product positions on the final day of the panel. Status and action are live formulas: change a threshold on Parameters and this list re-prioritises.
A4: SKU Key | B4: Store ID | C4: Product ID | D4: Inventory (units) | E4: Avg Daily Demand | F4: Days of Cover | G4: Reorder Point (units) | H4: Order Qty to Target (units) | I4: Units Actually Ordered | J4: Order Gap (units) | K4: Inventory Value ($) | L4: Stock Status | M4: Recommended Action | N4: Unit Price ($)
A5: S001-P0001 | B5: S001 | C5: P0001 | D5: 223 | E5: 128.71 | F5: =IFERROR(D5/E5,0) -> 1.7325771 | G5: =E5*Parameters!$B$6 -> 193.065 | H5: =MAX(0,E5*Parameters!$B$7-D5) -> 163.13 | I5: 93 | J5: =I5-H5 -> -70.13 | K5: =D5*N5 -> 12322.98 | L5: =IF(F5<Parameters!$B$5,"Critical",IF(F5<Parameters!$B$6,"Below Reorder",IF(F5<=Parameters!$B$7,"Healthy","Excess"))) -> Healthy | M5: =IF(L5="Critical","REPLENISH NOW",IF(L5="Below Reorder","REPLENISH",IF(L5="Healthy","MAINTAIN","REDUCE STOCK"))) -> MAINTAIN | N5: 55.26
A6: S001-P0002 | B6: S001 | C6: P0002 | D6: 217 | E6: 102.96 | F6: =IFERROR(D6/E6,0) -> 2.1076146 | G6: =E6*Parameters!$B$6 -> 154.44 | H6: =MAX(0,E6*Parameters!$B$7-D6) -> 91.88 | I6: 73 | J6: =I6-H6 -> -18.88 | K6: =D6*N6 -> 9730.28 | L6: =IF(F6<Parameters!$B$5,"Critical",IF(F6<Parameters!$B$6,"Below Reorder",IF(F6<=Parameters!$B$7,"Healthy","Excess"))) -> Healthy | M6: =IF(L6="Critical","REPLENISH NOW",IF(L6="Below Reorder","REPLENISH",IF(L6="Healthy","MAINTAIN","REDUCE STOCK"))) -> MAINTAIN | N6: 44.84
A7: S001-P0003 | B7: S001 | C7: P0003 | D7: 69 | E7: 137.14 | F7: =IFERROR(D7/E7,0) -> 0.50313548 | G7: =E7*Parameters!$B$6 -> 205.71 | H7: =MAX(0,E7*Parameters!$B$7-D7) -> 342.42 | I7: 191 | J7: =I7-H7 -> -151.42 | K7: =D7*N7 -> 1513.86 | L7: =IF(F7<Parameters!$B$5,"Critical",IF(F7<Parameters!$B$6,"Below Reorder",IF(F7<=Parameters!$B$7,"Healthy","Excess"))) -> Critical | M7: =IF(L7="Critical","REPLENISH NOW",IF(L7="Below Reorder","REPLENISH",IF(L7="Healthy","MAINTAIN","REDUCE STOCK"))) -> REPLENISH NOW | N7: 21.94
A8: S001-P0004 | B8: S001 | C8: P0004 | D8: 338 | E8: 151.14 | F8: =IFERROR(D8/E8,0) -> 2.2363372 | G8: =E8*Parameters!$B$6 -> 226.71 | H8: =MAX(0,E8*Parameters!$B$7-D8) -> 115.42 | I8: 152 | J8: =I8-H8 -> 36.58 | K8: =D8*N8 -> 29193.06 | L8: =IF(F8<Parameters!$B$5,"Critical",IF(F8<Parameters!$B$6,"Below Reorder",IF(F8<=Parameters!$B$7,"Healthy","Excess"))) -> Healthy | M8: =IF(L8="Critical","REPLENISH NOW",IF(L8="Below Reorder","REPLENISH",IF(L8="Healthy","MAINTAIN","REDUCE STOCK"))) -> MAINTAIN | N8: 86.37
A9: S001-P0005 | B9: S001 | C9: P0005 | D9: 471 | E9: 157.64 | F9: =IFERROR(D9/E9,0) -> 2.9878204 | G9: =E9*Parameters!$B$6 -> 236.46 | H9: =MAX(0,E9*Parameters!$B$7-D9) -> 1.92 | I9: 167 | J9: =I9-H9 -> 165.08 | K9: =D9*N9 -> 7338.18 | L9: =IF(F9<Parameters!$B$5,"Critical",IF(F9<Parameters!$B$6,"Below Reorder",IF(F9<=Parameters!$B$7,"Healthy","Excess"))) -> Healthy | M9: =IF(L9="Critical","REPLENISH NOW",IF(L9="Below Reorder","REPLENISH",IF(L9="Healthy","MAINTAIN","REDUCE STOCK"))) -> MAINTAIN | N9: 15.58
A10: S001-P0006 | B10: S001 | C10: P0006 | D10: 305 | E10: 105.82 | F10: =IFERROR(D10/E10,0) -> 2.8822529 | G10: =E10*Parameters!$B$6 -> 158.73 | H10: =MAX(0,E10*Parameters!$B$7-D10) -> 12.46 | I10: 114 | J10: =I10-H10 -> 101.54 | K10: =D10*N10 -> 19751.8 | L10: =IF(F10<Parameters!$B$5,"Critical",IF(F10<Parameters!$B$6,"Below Reorder",IF(F10<=Parameters!$B$7,"Healthy","Excess"))) -> Healthy | M10: =IF(L10="Critical","REPLENISH NOW",IF(L10="Below Reorder","REPLENISH",IF(L10="Healthy","MAINTAIN","REDUCE STOCK"))) -> MAINTAIN | N10: 64.76
A11: S001-P0007 | B11: S001 | C11: P0007 | D11: 256 | E11: 153.07 | F11: =IFERROR(D11/E11,0) -> 1.6724374 | G11: =E11*Parameters!$B$6 -> 229.605 | H11: =MAX(0,E11*Parameters!$B$7-D11) -> 203.21 | I11: 184 | J11: =I11-H11 -> -19.21 | K11: =D11*N11 -> 19824.64 | L11: =IF(F11<Parameters!$B$5,"Critical",IF(F11<Parameters!$B$6,"Below Reorder",IF(F11<=Parameters!$B$7,"Healthy","Excess"))) -> Healthy | M11: =IF(L11="Critical","REPLENISH NOW",IF(L11="Below Reorder","REPLENISH",IF(L11="Healthy","MAINTAIN","REDUCE STOCK"))) -> MAINTAIN | N11: 77.44
A12: S001-P0008 | B12: S001 | C12: P0008 | D12: 315 | E12: 131.36 | F12: =IFERROR(D12/E12,0) -> 2.3979903 | G12: =E12*Parameters!$B$6 -> 197.04 | H12: =MAX(0,E12*Parameters!$B$7-D12) -> 79.08 | I12: 108 | J12: =I12-H12 -> 28.92 | K12: =D12*N12 -> 9872.1 | L12: =IF(F12<Parameters!$B$5,"Critical",IF(F12<Parameters!$B$6,"Below Reorder",IF(F12<=Parameters!$B$7,"Healthy","Excess"))) -> Healthy | M12: =IF(L12="Critical","REPLENISH NOW",IF(L12="Below Reorder","REPLENISH",IF(L12="Healthy","MAINTAIN","REDUCE STOCK"))) -> MAINTAIN | N12: 31.34
A13: S001-P0009 | B13: S001 | C13: P0009 | D13: 167 | E13: 157.82 | F13: =IFERROR(D13/E13,0) -> 1.0581675 | G13: =E13*Parameters!$B$6 -> 236.73 | H13: =MAX(0,E13*Parameters!$B$7-D13) -> 306.46 | I13: 188 | J13: =I13-H13 -> -118.46 | K13: =D13*N13 -> 16165.6 | L13: =IF(F13<Parameters!$B$5,"Critical",IF(F13<Parameters!$B$6,"Below Reorder",IF(F13<=Parameters!$B$7,"Healthy","Excess"))) -> Below Reorder | M13: =IF(L13="Critical","REPLENISH NOW",IF(L13="Below Reorder","REPLENISH",IF(L13="Healthy","MAINTAIN","REDUCE STOCK"))) -> REPLENISH | N13: 96.8
A14: S001-P0010 | B14: S001 | C14: P0010 | D14: 167 | E14: 124.82 | F14: =IFERROR(D14/E14,0) -> 1.3379266 | G14: =E14*Parameters!$B$6 -> 187.23 | H14: =MAX(0,E14*Parameters!$B$7-D14) -> 207.46 | I14: 107 | J14: =I14-H14 -> -100.46 | K14: =D14*N14 -> 6838.65 | L14: =IF(F14<Parameters!$B$5,"Critical",IF(F14<Parameters!$B$6,"Below Reorder",IF(F14<=Parameters!$B$7,"Healthy","Excess"))) -> Below Reorder | M14: =IF(L14="Critical","REPLENISH NOW",IF(L14="Below Reorder","REPLENISH",IF(L14="Healthy","MAINTAIN","REDUCE STOCK"))) -> REPLENISH | N14: 40.95
A15: S001-P0011 | B15: S001 | C15: P0011 | D15: 449 | E15: 162.64 | F15: =IFERROR(D15/E15,0) -> 2.7606985 | G15: =E15*Parameters!$B$6 -> 243.96 | H15: =MAX(0,E15*Parameters!$B$7-D15) -> 38.92 | I15: 118 | J15: =I15-H15 -> 79.08 | K15: =D15*N15 -> 40809.61 | L15: =IF(F15<Parameters!$B$5,"Critical",IF(F15<Parameters!$B$6,"Below Reorder",IF(F15<=Parameters!$B$7,"Healthy","Excess"))) -> Healthy | M15: =IF(L15="Critical","REPLENISH NOW",IF(L15="Below Reorder","REPLENISH",IF(L15="Healthy","MAINTAIN","REDUCE STOCK"))) -> MAINTAIN | N15: 90.89
A16: S001-P0012 | B16: S001 | C16: P0012 | D16: 213 | E16: 143.11 | F16: =IFERROR(D16/E16,0) -> 1.4883656 | G16: =E16*Parameters!$B$6 -> 214.665 | H16: =MAX(0,E16*Parameters!$B$7-D16) -> 216.33 | I16: 175 | J16: =I16-H16 -> -41.33 | K16: =D16*N16 -> 8336.82 | L16: =IF(F16<Parameters!$B$5,"Critical",IF(F16<Parameters!$B$6,"Below Reorder",IF(F16<=Parameters!$B$7,"Healthy","Excess"))) -> Below Reorder | M16: =IF(L16="Critical","REPLENISH NOW",IF(L16="Below Reorder","REPLENISH",IF(L16="Healthy","MAINTAIN","REDUCE STOCK"))) -> REPLENISH | N16: 39.14
... A104: S005-P0020 | B104: S005 | C104: P0020 | D104: 117 | E104: 132.39 | F104: =IFERROR(D104/E104,0) -> 0.88375255 | G104: =E104*Parameters!$B$6 -> 198.585 | H104: =MAX(0,E104*Parameters!$B$7-D104) -> 280.17 | I104: 165 | J104: =I104-H104 -> -115.17 | K104: =D104*N104 -> 9171.63 | L104: =IF(F104<Parameters!$B$5,"Critical",IF(F104<Parameters!$B$6,"Below Reorder",IF(F104<=Parameters!$B$7,"Healthy","Excess"))) -> Critical | M104: =IF(L104="Critical","REPLENISH NOW",IF(L104="Below Reorder","REPLENISH",IF(L104="Healthy","MAINTAIN","REDUCE STOCK"))) -> REPLENISH NOW | N104: 78.39

Sheet SKU_Scorecard
A1: Store-SKU Scorecard - Exception Frequency Across 731 Days
A2: Grey columns are aggregated facts; white columns are live formulas. The 'Beyond Noise?' columns test whether a position's exception rate genuinely differs from the system rate or is just sampling variation.
A4: SKU Key | B4: Store ID | C4: Product ID | D4: Total Units Sold | E4: Avg Daily Demand | F4: Demand Std Dev | G4: Avg Inventory (units) | H4: Avg Price ($) | I4: Days Critical | J4: Days Excess | K4: Sold-Out Days | L4: Stockout-Risk Days | M4: Unserved Units | N4: Forecast Bias (units) | O4: Inventory Turnover (x/yr) | P4: Avg Days of Cover | Q4: Avg Inventory Value ($) | R4: % Days Critical | S4: % Days Excess | T4: Critical Beyond Noise? | U4: Excess Beyond Noise? | V4: Monitoring Priority
A5: S001-P0001 | B5: S001 | C5: P0001 | D5: 100371 | E5: 137.31 | F5: 108.19 | G5: 272.82 | H5: 55.16 | I5: 147 | J5: 138 | K5: 3 | L5: 30 | M5: 189.7 | N5: 5.76 | O5: =IFERROR(D5/G5/(Parameters!$B$8/Parameters!$B$9),0) -> 183.82514 | P5: =IFERROR(G5/E5,0) -> 1.986891 | Q5: =G5*H5 -> 15048.751 | R5: =100*I5/Parameters!$B$8 -> 20.109439 | S5: =100*J5/Parameters!$B$8 -> 18.878249 | T5: =IF(OR(R5<Parameters!$B$16,R5>Parameters!$B$17),"YES","no - within noise") -> no - within noise | U5: =IF(OR(S5<Parameters!$B$19,S5>Parameters!$B$20),"YES","no - within noise") -> no - within noise | V5: =IF(AND(T5="YES",R5>Parameters!$B$17),"Watch - stockout",IF(AND(U5="YES",S5>Parameters!$B$20),"Watch - excess capital","Routine")) -> Routine
A6: S001-P0002 | B6: S001 | C6: P0002 | D6: 95789 | E6: 131.04 | F6: 104.31 | G6: 272.66 | H6: 55.19 | I6: 124 | J6: 161 | K6: 6 | L6: 22 | M6: 183.5 | N6: 5.38 | O6: =IFERROR(D6/G6/(Parameters!$B$8/Parameters!$B$9),0) -> 175.53635 | P6: =IFERROR(G6/E6,0) -> 2.0807387 | Q6: =G6*H6 -> 15048.105 | R6: =100*I6/Parameters!$B$8 -> 16.963064 | S6: =100*J6/Parameters!$B$8 -> 22.024624 | T6: =IF(OR(R6<Parameters!$B$16,R6>Parameters!$B$17),"YES","no - within noise") -> no - within noise | U6: =IF(OR(S6<Parameters!$B$19,S6>Parameters!$B$20),"YES","no - within noise") -> no - within noise | V6: =IF(AND(T6="YES",R6>Parameters!$B$17),"Watch - stockout",IF(AND(U6="YES",S6>Parameters!$B$20),"Watch - excess capital","Routine")) -> Routine
A7: S001-P0003 | B7: S001 | C7: P0003 | D7: 103393 | E7: 141.44 | F7: 107.21 | G7: 274.54 | H7: 53.99 | I7: 139 | J7: 115 | K7: 3 | L7: 29 | M7: 171.3 | N7: 5.12 | O7: =IFERROR(D7/G7/(Parameters!$B$8/Parameters!$B$9),0) -> 188.17345 | P7: =IFERROR(G7/E7,0) -> 1.9410351 | Q7: =G7*H7 -> 14822.415 | R7: =100*I7/Parameters!$B$8 -> 19.015048 | S7: =100*J7/Parameters!$B$8 -> 15.731874 | T7: =IF(OR(R7<Parameters!$B$16,R7>Parameters!$B$17),"YES","no - within noise") -> no - within noise | U7: =IF(OR(S7<Parameters!$B$19,S7>Parameters!$B$20),"YES","no - within noise") -> no - within noise | V7: =IF(AND(T7="YES",R7>Parameters!$B$17),"Watch - stockout",IF(AND(U7="YES",S7>Parameters!$B$20),"Watch - excess capital","Routine")) -> Routine
A8: S001-P0004 | B8: S001 | C8: P0004 | D8: 103001 | E8: 140.9 | F8: 113.64 | G8: 275.91 | H8: 54.79 | I8: 138 | J8: 122 | K8: 2 | L8: 28 | M8: 147.8 | N8: 5.15 | O8: =IFERROR(D8/G8/(Parameters!$B$8/Parameters!$B$9),0) -> 186.52921 | P8: =IFERROR(G8/E8,0) -> 1.9581973 | Q8: =G8*H8 -> 15117.109 | R8: =100*I8/Parameters!$B$8 -> 18.878249 | S8: =100*J8/Parameters!$B$8 -> 16.689466 | T8: =IF(OR(R8<Parameters!$B$16,R8>Parameters!$B$17),"YES","no - within noise") -> no - within noise | U8: =IF(OR(S8<Parameters!$B$19,S8>Parameters!$B$20),"YES","no - within noise") -> no - within noise | V8: =IF(AND(T8="YES",R8>Parameters!$B$17),"Watch - stockout",IF(AND(U8="YES",S8>Parameters!$B$20),"Watch - excess capital","Routine")) -> Routine
A9: S001-P0005 | B9: S001 | C9: P0005 | D9: 97318 | E9: 133.13 | F9: 107.37 | G9: 269.33 | H9: 54.09 | I9: 131 | J9: 136 | K9: 4 | L9: 23 | M9: 148.8 | N9: 5.1 | O9: =IFERROR(D9/G9/(Parameters!$B$8/Parameters!$B$9),0) -> 180.54326 | P9: =IFERROR(G9/E9,0) -> 2.0230602 | Q9: =G9*H9 -> 14568.06 | R9: =100*I9/Parameters!$B$8 -> 17.920657 | S9: =100*J9/Parameters!$B$8 -> 18.604651 | T9: =IF(OR(R9<Parameters!$B$16,R9>Parameters!$B$17),"YES","no - within noise") -> no - within noise | U9: =IF(OR(S9<Parameters!$B$19,S9>Parameters!$B$20),"YES","no - within noise") -> no - within noise | V9: =IF(AND(T9="YES",R9>Parameters!$B$17),"Watch - stockout",IF(AND(U9="YES",S9>Parameters!$B$20),"Watch - excess capital","Routine")) -> Routine
A10: S001-P0006 | B10: S001 | C10: P0006 | D10: 95522 | E10: 130.67 | F10: 109.02 | G10: 272.95 | H10: 54.59 | I10: 136 | J10: 169 | K10: 3 | L10: 30 | M10: 224.3 | N10: 5.31 | O10: =IFERROR(D10/G10/(Parameters!$B$8/Parameters!$B$9),0) -> 174.86108 | P10: =IFERROR(G10/E10,0) -> 2.0888498 | Q10: =G10*H10 -> 14900.341 | R10: =100*I10/Parameters!$B$8 -> 18.604651 | S10: =100*J10/Parameters!$B$8 -> 23.119015 | T10: =IF(OR(R10<Parameters!$B$16,R10>Parameters!$B$17),"YES","no - within noise") -> no - within noise | U10: =IF(OR(S10<Parameters!$B$19,S10>Parameters!$B$20),"YES","no - within noise") -> no - within noise | V10: =IF(AND(T10="YES",R10>Parameters!$B$17),"Watch - stockout",IF(AND(U10="YES",S10>Parameters!$B$20),"Watch - excess capital","Routine")) -> Routine
A11: S001-P0007 | B11: S001 | C11: P0007 | D11: 100749 | E11: 137.82 | F11: 111.2 | G11: 278.41 | H11: 54.12 | I11: 143 | J11: 136 | K11: 8 | L11: 21 | M11: 172 | N11: 4.63 | O11: =IFERROR(D11/G11/(Parameters!$B$8/Parameters!$B$9),0) -> 180.81263 | P11: =IFERROR(G11/E11,0) -> 2.0200987 | Q11: =G11*H11 -> 15067.549 | R11: =100*I11/Parameters!$B$8 -> 19.562244 | S11: =100*J11/Parameters!$B$8 -> 18.604651 | T11: =IF(OR(R11<Parameters!$B$16,R11>Parameters!$B$17),"YES","no - within noise") -> no - within noise | U11: =IF(OR(S11<Parameters!$B$19,S11>Parameters!$B$20),"YES","no - within noise") -> no - within noise | V11: =IF(AND(T11="YES",R11>Parameters!$B$17),"Watch - stockout",IF(AND(U11="YES",S11>Parameters!$B$20),"Watch - excess capital","Routine")) -> Routine
A12: S001-P0008 | B12: S001 | C12: P0008 | D12: 100244 | E12: 137.13 | F12: 108.7 | G12: 269.92 | H12: 55.15 | I12: 132 | J12: 126 | K12: 1 | L12: 23 | M12: 167.7 | N12: 4.58 | O12: =IFERROR(D12/G12/(Parameters!$B$8/Parameters!$B$9),0) -> 185.56504 | P12: =IFERROR(G12/E12,0) -> 1.9683512 | Q12: =G12*H12 -> 14886.088 | R12: =100*I12/Parameters!$B$8 -> 18.057456 | S12: =100*J12/Parameters!$B$8 -> 17.236662 | T12: =IF(OR(R12<Parameters!$B$16,R12>Parameters!$B$17),"YES","no - within noise") -> no - within noise | U12: =IF(OR(S12<Parameters!$B$19,S12>Parameters!$B$20),"YES","no - within noise") -> no - within noise | V12: =IF(AND(T12="YES",R12>Parameters!$B$17),"Watch - stockout",IF(AND(U12="YES",S12>Parameters!$B$20),"Watch - excess capital","Routine")) -> Routine
A13: S001-P0009 | B13: S001 | C13: P0009 | D13: 96080 | E13: 131.44 | F13: 107.09 | G13: 270.53 | H13: 55.73 | I13: 132 | J13: 157 | K13: 6 | L13: 26 | M13: 162.5 | N13: 4.91 | O13: =IFERROR(D13/G13/(Parameters!$B$8/Parameters!$B$9),0) -> 177.45589 | P13: =IFERROR(G13/E13,0) -> 2.0582015 | Q13: =G13*H13 -> 15076.637 | R13: =100*I13/Parameters!$B$8 -> 18.057456 | S13: =100*J13/Parameters!$B$8 -> 21.477428 | T13: =IF(OR(R13<Parameters!$B$16,R13>Parameters!$B$17),"YES","no - within noise") -> no - within noise | U13: =IF(OR(S13<Parameters!$B$19,S13>Parameters!$B$20),"YES","no - within noise") -> no - within noise | V13: =IF(AND(T13="YES",R13>Parameters!$B$17),"Watch - stockout",IF(AND(U13="YES",S13>Parameters!$B$20),"Watch - excess capital","Routine")) -> Routine
A14: S001-P0010 | B14: S001 | C14: P0010 | D14: 96756 | E14: 132.36 | F14: 105.92 | G14: 274.89 | H14: 57.41 | I14: 127 | J14: 172 | K14: 3 | L14: 23 | M14: 208.3 | N14: 4.29 | O14: =IFERROR(D14/G14/(Parameters!$B$8/Parameters!$B$9),0) -> 175.87002 | P14: =IFERROR(G14/E14,0) -> 2.0768359 | Q14: =G14*H14 -> 15781.435 | R14: =100*I14/Parameters!$B$8 -> 17.373461 | S14: =100*J14/Parameters!$B$8 -> 23.529412 | T14: =IF(OR(R14<Parameters!$B$16,R14>Parameters!$B$17),"YES","no - within noise") -> no - within noise | U14: =IF(OR(S14<Parameters!$B$19,S14>Parameters!$B$20),"YES","no - within noise") -> YES | V14: =IF(AND(T14="YES",R14>Parameters!$B$17),"Watch - stockout",IF(AND(U14="YES",S14>Parameters!$B$20),"Watch - excess capital","Routine")) -> Watch - excess capital
A15: S001-P0011 | B15: S001 | C15: P0011 | D15: 96852 | E15: 132.49 | F15: 109.9 | G15: 269.19 | H15: 54.4 | I15: 134 | J15: 170 | K15: 6 | L15: 33 | M15: 206.7 | N15: 4.66 | O15: =IFERROR(D15/G15/(Parameters!$B$8/Parameters!$B$9),0) -> 179.77219 | P15: =IFERROR(G15/E15,0) -> 2.031776 | Q15: =G15*H15 -> 14643.936 | R15: =100*I15/Parameters!$B$8 -> 18.331053 | S15: =100*J15/Parameters!$B$8 -> 23.255814 | T15: =IF(OR(R15<Parameters!$B$16,R15>Parameters!$B$17),"YES","no - within noise") -> no - within noise | U15: =IF(OR(S15<Parameters!$B$19,S15>Parameters!$B$20),"YES","no - within noise") -> YES | V15: =IF(AND(T15="YES",R15>Parameters!$B$17),"Watch - stockout",IF(AND(U15="YES",S15>Parameters!$B$20),"Watch - excess capital","Routine")) -> Watch - excess capital
A16: S001-P0012 | B16: S001 | C16: P0012 | D16: 93854 | E16: 128.39 | F16: 102.24 | G16: 266.76 | H16: 53.88 | I16: 141 | J16: 179 | K16: 2 | L16: 21 | M16: 121.4 | N16: 4.6 | O16: =IFERROR(D16/G16/(Parameters!$B$8/Parameters!$B$9),0) -> 175.79436 | P16: =IFERROR(G16/E16,0) -> 2.0777319 | Q16: =G16*H16 -> 14373.029 | R16: =100*I16/Parameters!$B$8 -> 19.288646 | S16: =100*J16/Parameters!$B$8 -> 24.487004 | T16: =IF(OR(R16<Parameters!$B$16,R16>Parameters!$B$17),"YES","no - within noise") -> no - within noise | U16: =IF(OR(S16<Parameters!$B$19,S16>Parameters!$B$20),"YES","no - within noise") -> YES | V16: =IF(AND(T16="YES",R16>Parameters!$B$17),"Watch - stockout",IF(AND(U16="YES",S16>Parameters!$B$20),"Watch - excess capital","Routine")) -> Watch - excess capital
... A104: S005-P0020 | B104: S005 | C104: P0020 | D104: 101370 | E104: 138.67 | F104: 111.14 | G104: 283.9 | H104: 55.73 | I104: 127 | J104: 149 | K104: 10 | L104: 19 | M104: 165.4 | N104: 4.6 | O104: =IFERROR(D104/G104/(Parameters!$B$8/Parameters!$B$9),0) -> 178.40906 | P104: =IFERROR(G104/E104,0) -> 2.0473066 | Q104: =G104*H104 -> 15821.747 | R104: =100*I104/Parameters!$B$8 -> 17.373461 | S104: =100*J104/Parameters!$B$8 -> 20.383037 | T104: =IF(OR(R104<Parameters!$B$16,R104>Parameters!$B$17),"YES","no - within noise") -> no - within noise | U104: =IF(OR(S104<Parameters!$B$19,S104>Parameters!$B$20),"YES","no - within noise") -> no - within noise | V104: =IF(AND(T104="YES",R104>Parameters!$B$17),"Watch - stockout",IF(AND(U104="YES",S104>Parameters!$B$20),"Watch - excess capital","Routine")) -> Routine

Sheet Monthly_Summary
A1: Monthly Demand and Inventory Summary
A2: Complete Month = 0 marks a partial period. January 2024 holds a single day (2024-01-01) and is excluded from growth calculations.
A4: Year-Month | B4: Units Sold | C4: Revenue ($) | D4: Avg Inventory (units) | E4: Avg Days of Cover | F4: Critical Position-Days | G4: Excess Position-Days | H4: Avg Excess Value ($) | I4: Forecast Bias (units) | J4: Position Days | K4: Complete Month | L4: MoM Units Growth
A5: 2022-01 | B5: 419938 | C5: 20919533 | D5: 272.01 | E5: 2.05 | F5: 586 | G5: 617 | H5: 685.05 | I5: 5.05 | J5: 3100 | K5: 1
A6: 2022-02 | B6: 391052 | C6: 19061033 | D6: 275.8 | E6: 2.05 | F6: 545 | G6: 549 | H6: 664.73 | I6: 5.16 | J6: 2800 | K6: 1 | L6: =IF(OR(K6=0,K5=0),"",IFERROR(B6/B5-1,"")) -> -0.068786345
A7: 2022-03 | B7: 426073 | C7: 21522683 | D7: 274.81 | E7: 2.01 | F7: 576 | G7: 548 | H7: 589.76 | I7: 5.16 | J7: 3100 | K7: 1 | L7: =IF(OR(K7=0,K6=0),"",IFERROR(B7/B6-1,"")) -> 0.089555865
A8: 2022-04 | B8: 407380 | C8: 20314403 | D8: 272.19 | E8: 2.01 | F8: 576 | G8: 559 | H8: 626.93 | I8: 5.02 | J8: 3000 | K8: 1 | L8: =IF(OR(K8=0,K7=0),"",IFERROR(B8/B7-1,"")) -> -0.043872764
A9: 2022-05 | B9: 414799 | C9: 20542562 | D9: 271.75 | E9: 2.05 | F9: 574 | G9: 632 | H9: 664.17 | I9: 4.82 | J9: 3100 | K9: 1 | L9: =IF(OR(K9=0,K8=0),"",IFERROR(B9/B8-1,"")) -> 0.018211498
A10: 2022-06 | B10: 415509 | C10: 20981787 | D10: 278.93 | E10: 2.1 | F10: 524 | G10: 636 | H10: 776.81 | I10: 4.99 | J10: 3000 | K10: 1 | L10: =IF(OR(K10=0,K9=0),"",IFERROR(B10/B9-1,"")) -> 0.0017116724
A11: 2022-07 | B11: 426628 | C11: 21293910 | D11: 274.61 | E11: 2 | F11: 588 | G11: 529 | H11: 536.77 | I11: 5.01 | J11: 3100 | K11: 1 | L11: =IF(OR(K11=0,K10=0),"",IFERROR(B11/B10-1,"")) -> 0.02675995
A12: 2022-08 | B12: 424916 | C12: 21055281 | D12: 275.25 | E12: 2.02 | F12: 572 | G12: 549 | H12: 555.84 | I12: 4.98 | J12: 3100 | K12: 1 | L12: =IF(OR(K12=0,K11=0),"",IFERROR(B12/B11-1,"")) -> -0.0040128637
A13: 2022-09 | B13: 411610 | C13: 20628911 | D13: 278.38 | E13: 2.06 | F13: 520 | G13: 564 | H13: 593.42 | I13: 5.15 | J13: 3000 | K13: 1 | L13: =IF(OR(K13=0,K12=0),"",IFERROR(B13/B12-1,"")) -> -0.031314424
A14: 2022-10 | B14: 426863 | C14: 21147496 | D14: 275.54 | E14: 2.04 | F14: 596 | G14: 580 | H14: 658.07 | I14: 4.93 | J14: 3100 | K14: 1 | L14: =IF(OR(K14=0,K13=0),"",IFERROR(B14/B13-1,"")) -> 0.037056923
A15: 2022-11 | B15: 414535 | C15: 20719137 | D15: 276.59 | E15: 2.05 | F15: 569 | G15: 584 | H15: 687.14 | I15: 4.99 | J15: 3000 | K15: 1 | L15: =IF(OR(K15=0,K14=0),"",IFERROR(B15/B14-1,"")) -> -0.02888046
A16: 2022-12 | B16: 412321 | C16: 20268137 | D16: 271.94 | E16: 2.04 | F16: 602 | G16: 575 | H16: 688.24 | I16: 5.05 | J16: 3100 | K16: 1 | L16: =IF(OR(K16=0,K15=0),"",IFERROR(B16/B15-1,"")) -> -0.0053409242
A17: 2023-01 | B17: 423408 | C17: 20723763 | D17: 275.42 | E17: 2.07 | F17: 541 | G17: 623 | H17: 682.82 | I17: 4.98 | J17: 3100 | K17: 1 | L17: =IF(OR(K17=0,K16=0),"",IFERROR(B17/B16-1,"")) -> 0.026889244
... A29: 2024-01 | B29: 13244 | C29: 628142.78 | D29: 264.76 | E29: 1.97 | F29: 17 | G29: 15 | H29: 396.81 | I29: 4.78 | J29: 100 | K29: 0 | L29: =IF(OR(K29=0,K28=0),"",IFERROR(B29/B28-1,""))

Sheet Store_Summary
A1: Store Roll-Up
A2: Every figure is a SUMIF / AVERAGEIF / COUNTIFS against SKU_Scorecard.
A4: Store ID | B4: SKU Positions | C4: Total Units Sold | D4: Avg Inventory Value ($) | E4: Avg Days of Cover | F4: Avg Turnover (x/yr) | G4: Avg % Days Critical | H4: Avg % Days Excess | I4: Total Unserved Units | J4: Positions Flagged for Watch
A5: S001 | B5: =COUNTIF(SKU_Scorecard!$B$5:$B$104,$A5) -> 20 | C5: =SUMIF(SKU_Scorecard!$B$5:$B$104,$A5,SKU_Scorecard!$D$5:$D$104) -> 1975750 | D5: =SUMIF(SKU_Scorecard!$B$5:$B$104,$A5,SKU_Scorecard!$Q$5:$Q$104) -> 301073.96 | E5: =AVERAGEIF(SKU_Scorecard!$B$5:$B$104,$A5,SKU_Scorecard!$P$5:$P$104) -> 2.0234529 | F5: =AVERAGEIF(SKU_Scorecard!$B$5:$B$104,$A5,SKU_Scorecard!$O$5:$O$104) -> 180.59981 | G5: =AVERAGEIF(SKU_Scorecard!$B$5:$B$104,$A5,SKU_Scorecard!$R$5:$R$104) -> 18.413133 | H5: =AVERAGEIF(SKU_Scorecard!$B$5:$B$104,$A5,SKU_Scorecard!$S$5:$S$104) -> 19.883721 | I5: =SUMIF(SKU_Scorecard!$B$5:$B$104,$A5,SKU_Scorecard!$M$5:$M$104) -> 3304.4 | J5: =COUNTIFS(SKU_Scorecard!$B$5:$B$104,$A5,SKU_Scorecard!$V$5:$V$104,"Watch*") -> 3
A6: S002 | B6: =COUNTIF(SKU_Scorecard!$B$5:$B$104,$A6) -> 20 | C6: =SUMIF(SKU_Scorecard!$B$5:$B$104,$A6,SKU_Scorecard!$D$5:$D$104) -> 1987715 | D6: =SUMIF(SKU_Scorecard!$B$5:$B$104,$A6,SKU_Scorecard!$Q$5:$Q$104) -> 302595.7 | E6: =AVERAGEIF(SKU_Scorecard!$B$5:$B$104,$A6,SKU_Scorecard!$P$5:$P$104) -> 2.0120206 | F6: =AVERAGEIF(SKU_Scorecard!$B$5:$B$104,$A6,SKU_Scorecard!$O$5:$O$104) -> 181.66451 | G6: =AVERAGEIF(SKU_Scorecard!$B$5:$B$104,$A6,SKU_Scorecard!$R$5:$R$104) -> 18.912449 | H6: =AVERAGEIF(SKU_Scorecard!$B$5:$B$104,$A6,SKU_Scorecard!$S$5:$S$104) -> 19.199726 | I6: =SUMIF(SKU_Scorecard!$B$5:$B$104,$A6,SKU_Scorecard!$M$5:$M$104) -> 3397.9 | J6: =COUNTIFS(SKU_Scorecard!$B$5:$B$104,$A6,SKU_Scorecard!$V$5:$V$104,"Watch*") -> 0
A7: S003 | B7: =COUNTIF(SKU_Scorecard!$B$5:$B$104,$A7) -> 20 | C7: =SUMIF(SKU_Scorecard!$B$5:$B$104,$A7,SKU_Scorecard!$D$5:$D$104) -> 2022696 | D7: =SUMIF(SKU_Scorecard!$B$5:$B$104,$A7,SKU_Scorecard!$Q$5:$Q$104) -> 305009.85 | E7: =AVERAGEIF(SKU_Scorecard!$B$5:$B$104,$A7,SKU_Scorecard!$P$5:$P$104) -> 2.0030434 | F7: =AVERAGEIF(SKU_Scorecard!$B$5:$B$104,$A7,SKU_Scorecard!$O$5:$O$104) -> 182.4895 | G7: =AVERAGEIF(SKU_Scorecard!$B$5:$B$104,$A7,SKU_Scorecard!$R$5:$R$104) -> 18.440492 | H7: =AVERAGEIF(SKU_Scorecard!$B$5:$B$104,$A7,SKU_Scorecard!$S$5:$S$104) -> 18.351573 | I7: =SUMIF(SKU_Scorecard!$B$5:$B$104,$A7,SKU_Scorecard!$M$5:$M$104) -> 3391.6 | J7: =COUNTIFS(SKU_Scorecard!$B$5:$B$104,$A7,SKU_Scorecard!$V$5:$V$104,"Watch*") -> 2
A8: S004 | B8: =COUNTIF(SKU_Scorecard!$B$5:$B$104,$A8) -> 20 | C8: =SUMIF(SKU_Scorecard!$B$5:$B$104,$A8,SKU_Scorecard!$D$5:$D$104) -> 1979245 | D8: =SUMIF(SKU_Scorecard!$B$5:$B$104,$A8,SKU_Scorecard!$Q$5:$Q$104) -> 301381.37 | E8: =AVERAGEIF(SKU_Scorecard!$B$5:$B$104,$A8,SKU_Scorecard!$P$5:$P$104) -> 2.0126112 | F8: =AVERAGEIF(SKU_Scorecard!$B$5:$B$104,$A8,SKU_Scorecard!$O$5:$O$104) -> 181.5701 | G8: =AVERAGEIF(SKU_Scorecard!$B$5:$B$104,$A8,SKU_Scorecard!$R$5:$R$104) -> 18.898769 | H8: =AVERAGEIF(SKU_Scorecard!$B$5:$B$104,$A8,SKU_Scorecard!$S$5:$S$104) -> 19.302326 | I8: =SUMIF(SKU_Scorecard!$B$5:$B$104,$A8,SKU_Scorecard!$M$5:$M$104) -> 3774.4 | J8: =COUNTIFS(SKU_Scorecard!$B$5:$B$104,$A8,SKU_Scorecard!$V$5:$V$104,"Watch*") -> 0
A9: S005 | B9: =COUNTIF(SKU_Scorecard!$B$5:$B$104,$A9) -> 20 | C9: =SUMIF(SKU_Scorecard!$B$5:$B$104,$A9,SKU_Scorecard!$D$5:$D$104) -> 2010176 | D9: =SUMIF(SKU_Scorecard!$B$5:$B$104,$A9,SKU_Scorecard!$Q$5:$Q$104) -> 306330.47 | E9: =AVERAGEIF(SKU_Scorecard!$B$5:$B$104,$A9,SKU_Scorecard!$P$5:$P$104) -> 2.0120613 | F9: =AVERAGEIF(SKU_Scorecard!$B$5:$B$104,$A9,SKU_Scorecard!$O$5:$O$104) -> 181.63808 | G9: =AVERAGEIF(SKU_Scorecard!$B$5:$B$104,$A9,SKU_Scorecard!$R$5:$R$104) -> 18.72093 | H9: =AVERAGEIF(SKU_Scorecard!$B$5:$B$104,$A9,SKU_Scorecard!$S$5:$S$104) -> 18.823529 | I9: =SUMIF(SKU_Scorecard!$B$5:$B$104,$A9,SKU_Scorecard!$M$5:$M$104) -> 3425.3 | J9: =COUNTIFS(SKU_Scorecard!$B$5:$B$104,$A9,SKU_Scorecard!$V$5:$V$104,"Watch*") -> 0

Sheet KPI_Dashboard
A1: Headline KPIs
A2: All values are formulas over the other sheets. Nothing is hardcoded.
A4: KPI | B4: Value | C4: Definition
A5: PERIOD TOTALS
A6: Total Units Sold | B6: =SUM(Monthly_Summary!$B$5:$B$29) -> 9975582 | C6: All 100 positions across 731 days.
A7: Total Revenue | B7: =SUM(Monthly_Summary!$C$5:$C$29) -> 4.9497137e+08 | C7: Units sold x price x (1 - discount).
A8: Total Inventory Value on Hand | B8: =SUM(SKU_Scorecard!$Q$5:$Q$104) -> 1516391.4 | C8: Average daily value across all positions, at retail. No cost column exists.
A9: INVENTORY EFFICIENCY
A10: Avg Days of Cover | B10: =AVERAGE(SKU_Scorecard!$P$5:$P$104) -> 2.0126379 | C10: Average inventory divided by average daily demand.
A11: Avg Inventory Turnover (x/yr) | B11: =AVERAGE(SKU_Scorecard!$O$5:$O$104) -> 181.5924 | C11: Annualised. High because cover sits near two days - a fast-moving retail profile.
A12: System Critical Rate (%) | B12: =AVERAGE(SKU_Scorecard!$R$5:$R$104) -> 18.677155 | C12: Share of position-days below one day of cover.
A13: System Excess Rate (%) | B13: =AVERAGE(SKU_Scorecard!$S$5:$S$104) -> 19.112175 | C13: Share of position-days above target cover.
A14: SERVICE RISK
A15: Total Sold-Out Days | B15: =SUM(SKU_Scorecard!$K$5:$K$104) -> 369 | C15: Position-days that ended with zero stock; true demand was censored.
A16: Total Stockout-Risk Days | B16: =SUM(SKU_Scorecard!$L$5:$L$104) -> 2585 | C16: Position-days where forecast demand exceeded stock on hand.
A17: Total Unserved Units | B17: =SUM(SKU_Scorecard!$M$5:$M$104) -> 17293.6 | C17: Forecast demand the position could not have covered.
A18: FORECAST QUALITY
A19: Avg Forecast Bias (units/day) | B19: =AVERAGE(SKU_Scorecard!$N$5:$N$104) -> 5.0299 | C19: Positive means the supplied forecast runs above what actually sold.
A20: LATEST-DAY ACTION LIST
A21: Positions: REPLENISH NOW | B21: =COUNTIF(Action_Register!$L$5:$L$104,"Critical") -> 17 | C21: Below one day of cover on 2024-01-01.
A22: Positions: REPLENISH | B22: =COUNTIF(Action_Register!$L$5:$L$104,"Below Reorder") -> 20 | C22: Between the critical and reorder thresholds.
A23: Positions: MAINTAIN | B23: =COUNTIF(Action_Register!$L$5:$L$104,"Healthy") -> 48 | C23: Between reorder and target cover.
A24: Positions: REDUCE STOCK | B24: =COUNTIF(Action_Register!$L$5:$L$104,"Excess") -> 15 | C24: Above target cover.
A25: Units to Order Today | B25: =SUM(Action_Register!$H$5:$H$104) -> 14845.27 | C25: Units required to bring every position up to target cover.
A26: Today's Order Gap (units) | B26: =SUM(Action_Register!$J$5:$J$104) -> -3611.27 | C26: Actual order quantity minus requirement. Negative means under-ordering versus need.
A27: MONITORING
A28: Positions Flagged for Watch | B28: =COUNTIF(SKU_Scorecard!$V$5:$V$104,"Watch*") -> 5 | C28: Positions whose exception rate is genuinely outside the noise band.
A29: Positions Classed Routine | B29: =COUNTIF(SKU_Scorecard!$V$5:$V$104,"Routine") -> 95 | C29: Exception rate indistinguishable from the system average.

Sheet Data_Dictionary
A1: Data Dictionary
A3: Field | B3: Origin | C3: Type | D3: Definition / Note
A4: Date | B4: Source | C4: Date | D4: 2022-01-01 to 2024-01-01. 731 consecutive days, no gaps.
A5: Store ID | B5: Source | C5: Text | D5: S001-S005. Five stores.
A6: Product ID | B6: Source | C6: Text | D6: P0001-P0020. Twenty products, each stocked in all five stores.
A7: Category | B7: Source | C7: Text | D7: Five values. WARNING: varies row-to-row for the same product, so it is a transaction label, not a product attribute.
A8: Region | B8: Source | C8: Text | D8: Four values. WARNING: varies row-to-row for the same store, so it is not a store attribute.
A9: Inventory Level | B9: Source | C9: Integer | D9: Units on hand, daily snapshot.
A10: Units Sold | B10: Source | C10: Integer | D10: Units sold that day. Never exceeds Inventory Level.
A11: Units Ordered | B11: Source | C11: Integer | D11: Units ordered that day, 20-200. Uncorrelated with demand or stock position (|r| < 0.002).
A12: Demand Forecast | B12: Source | C12: Decimal | D12: Supplied forecast. Carries a systematic upward bias of about 5 units.
A13: Price | B13: Source | C13: Decimal | D13: Shelf price per unit, roughly $10-$100.
A14: Discount | B14: Source | C14: Integer | D14: Whole-number percent: 0, 5, 10, 15 or 20.
... A35: Recommended_Action | B35: Derived | C35: Text | D35: REPLENISH NOW / REPLENISH / MAINTAIN / REDUCE STOCK.

Sheet Raw_Sample
A1: Source Data - First 500 Rows
A2: Reference only. The full 73,100-row file is at data/raw/retail_store_inventory.csv.
A4: Date | B4: Store ID | C4: Product ID | D4: Category | E4: Region | F4: Inventory Level | G4: Units Sold | H4: Units Ordered | I4: Demand Forecast | J4: Price | K4: Discount | L4: Weather Condition | M4: Holiday/Promotion | N4: Competitor Pricing | O4: Seasonality
A5: 2022-01-01 | B5: S001 | C5: P0001 | D5: Groceries | E5: North | F5: 231 | G5: 127 | H5: 55 | I5: 135.47 | J5: 33.5 | K5: 20 | L5: Rainy | M5: 0 | N5: 29.69 | O5: Autumn
A6: 2022-01-01 | B6: S001 | C6: P0002 | D6: Toys | E6: South | F6: 204 | G6: 150 | H6: 66 | I6: 144.04 | J6: 63.01 | K6: 20 | L6: Sunny | M6: 0 | N6: 66.16 | O6: Autumn
A7: 2022-01-01 | B7: S001 | C7: P0003 | D7: Toys | E7: West | F7: 102 | G7: 65 | H7: 51 | I7: 74.02 | J7: 27.99 | K7: 10 | L7: Sunny | M7: 1 | N7: 31.32 | O7: Summer
A8: 2022-01-01 | B8: S001 | C8: P0004 | D8: Toys | E8: North | F8: 469 | G8: 61 | H8: 164 | I8: 62.18 | J8: 32.72 | K8: 10 | L8: Cloudy | M8: 1 | N8: 34.74 | O8: Autumn
A9: 2022-01-01 | B9: S001 | C9: P0005 | D9: Electronics | E9: East | F9: 166 | G9: 14 | H9: 135 | I9: 9.26 | J9: 73.64 | K9: 0 | L9: Sunny | M9: 0 | N9: 68.95 | O9: Summer
A10: 2022-01-01 | B10: S001 | C10: P0006 | D10: Groceries | E10: South | F10: 138 | G10: 128 | H10: 102 | I10: 139.82 | J10: 76.83 | K10: 10 | L10: Sunny | M10: 1 | N10: 79.35 | O10: Winter
A11: 2022-01-01 | B11: S001 | C11: P0007 | D11: Furniture | E11: East | F11: 359 | G11: 97 | H11: 167 | I11: 108.92 | J11: 34.16 | K11: 10 | L11: Rainy | M11: 1 | N11: 36.55 | O11: Winter
A12: 2022-01-01 | B12: S001 | C12: P0008 | D12: Clothing | E12: North | F12: 380 | G12: 312 | H12: 54 | I12: 329.73 | J12: 97.99 | K12: 5 | L12: Cloudy | M12: 0 | N12: 100.09 | O12: Spring
A13: 2022-01-01 | B13: S001 | C13: P0009 | D13: Electronics | E13: West | F13: 183 | G13: 175 | H13: 135 | I13: 174.15 | J13: 20.74 | K13: 10 | L13: Cloudy | M13: 0 | N13: 17.66 | O13: Autumn
A14: 2022-01-01 | B14: S001 | C14: P0010 | D14: Toys | E14: South | F14: 108 | G14: 28 | H14: 196 | I14: 24.47 | J14: 59.99 | K14: 0 | L14: Rainy | M14: 1 | N14: 61.21 | O14: Winter
A15: 2022-01-01 | B15: S001 | C15: P0011 | D15: Furniture | E15: South | F15: 258 | G15: 150 | H15: 153 | I15: 152.74 | J15: 58.53 | K15: 10 | L15: Sunny | M15: 1 | N15: 61.42 | O15: Spring
A16: 2022-01-01 | B16: S001 | C16: P0012 | D16: Clothing | E16: West | F16: 66 | G16: 24 | H16: 70 | I16: 26.75 | J16: 58.25 | K16: 20 | L16: Snowy | M16: 0 | N16: 62.21 | O16: Spring
... A504: 2022-01-05 | B504: S005 | C504: P0020 | D504: Groceries | E504: South | F504: 243 | G504: 36 | H504: 107 | I504: 47.12 | J504: 53.65 | K504: 20 | L504: Cloudy | M504: 1 | N504: 49.72 | O504: Winter
